LICENSE.md
MANIFEST.in
README.md
setup.py
Better_Than_You_Found_It.egg-info/PKG-INFO
Better_Than_You_Found_It.egg-info/SOURCES.txt
Better_Than_You_Found_It.egg-info/dependency_links.txt
Better_Than_You_Found_It.egg-info/entry_points.txt
Better_Than_You_Found_It.egg-info/not-zip-safe
Better_Than_You_Found_It.egg-info/requires.txt
Better_Than_You_Found_It.egg-info/top_level.txt
pep8radius/__init__.py
pep8radius/diff.py
pep8radius/main.py
pep8radius/radius.py
pep8radius/shell.py
pep8radius/vcs.py
tests/README.md
tests/__init__.py
tests/diff1.txt
tests/test_diff.py
tests/test_main.py
tests/test_radius.py
tests/test_vcs.py
tests/util.py
tests/util_vcs.py