Metadata-Version: 1.1
Name: Better-Than-You-Found-It
Version: 0.9.1
Summary: PEP8 clean only the parts of the files which you have touched since the last commit, a previous commit or (the merge-base of) a branch.
Home-page: https://github.com/hayd/pep8radius
Author: Andy Hayden
Author-email: andyhayden1@gmail.com
License: MIT License
Keywords: automation,pep8,format,autopep8,git,hg,mercurial,bzr
Platform: UNKNOWN
Classifier: Development Status :: 4 - Beta
Classifier: Environment :: Console
Classifier: Intended Audience :: Developers
Classifier: License :: OSI Approved :: MIT License
Classifier: Operating System :: OS Independent
Classifier: Programming Language :: Python
Classifier: Programming Language :: Python :: 2
Classifier: Programming Language :: Python :: 2.6
Classifier: Programming Language :: Python :: 2.7
Classifier: Programming Language :: Python :: 3
Classifier: Programming Language :: Python :: 3.2
Classifier: Programming Language :: Python :: 3.3
Classifier: Programming Language :: Python :: 3.4
Classifier: Topic :: Software Development :: Libraries :: Python Modules
Classifier: Topic :: Software Development :: Quality Assurance
Classifier: Topic :: Software Development :: Version Control
